docchain/__init__.py
docchain/blocks/__init__.py
docchain/blocks/base.py
docchain/blocks/json_schema.py
docchain/blocks/pydantic.py
docchain/blocks/text.py
docchain/blocks/ui_schema.py
docchain/documents.py
docchain/exceptions.py
docchain/generator.py
docchain/middleware/__init__.py
docchain/middleware/base.py
docchain/middleware/collect_openai_stats.py
docchain/middleware/save_document.py
docchain/models/__init__.py
docchain/models/gpt.py
docchain/output_parsers/__init__.py
docchain/output_parsers/json_schema.py
docchain/output_parsers/ui_schema.py
docchain/settings.py
docchain/specs.py
docchain/utils.py
docchain-0.0.7.dist-info/METADATA
docchain-0.0.7.dist-info/WHEEL
docchain-0.0.7.dist-info/RECORD
