Metadata-Version: 2.1
Name: docchain
Version: 0.0.7
Summary: 
Author: Artem Kolesnikov
Author-email: tyomo4ka@gmail.com
Requires-Python: >=3.10,<4.0
Classifier: Programming Language :: Python :: 3
Classifier: Programming Language :: Python :: 3.10
Classifier: Programming Language :: Python :: 3.11
Requires-Dist: fsspec (>=2023.5.0,<2024.0.0)
Requires-Dist: jinja2 (>=3.1.2,<4.0.0)
Requires-Dist: jsonschema (>=4.17.3,<5.0.0)
Requires-Dist: langchain (>=0.0.167,<0.0.168)
Requires-Dist: openai (>=0.27.6,<0.28.0)
Requires-Dist: pydantic (>=1.10.7,<2.0.0)
